porthos/__init__.py
porthos/status.py
porthos/client/__init__.py
porthos/client/call.py
porthos/client/response.py
porthos_python-0.0.3.dist-info/DESCRIPTION.rst
porthos_python-0.0.3.dist-info/METADATA
porthos_python-0.0.3.dist-info/RECORD
porthos_python-0.0.3.dist-info/WHEEL
porthos_python-0.0.3.dist-info/metadata.json
porthos_python-0.0.3.dist-info/top_level.txt
